setup.py
PyWITS/Globals.py
PyWITS/Receiver.py
PyWITS/ReceiverValidation.py
PyWITS/Simulation.py
PyWITS/Transceiver.py
PyWITS/Transmitter.py
PyWITS/__init__.py
PyWITS/test.py
PyWITS.egg-info/PKG-INFO
PyWITS.egg-info/SOURCES.txt
PyWITS.egg-info/dependency_links.txt
PyWITS.egg-info/requires.txt
PyWITS.egg-info/top_level.txt
PyWITS/Objects/DataItem.py
PyWITS/Objects/DataRecord.py
PyWITS/Objects/DataSet.py
PyWITS/Objects/Identifier.py
PyWITS/Objects/LogicalRecord.py
PyWITS/Objects/PhysicalRecord.py
PyWITS/Objects/PyWITSObject.py
PyWITS/Objects/RecordItem.py
PyWITS/Objects/RecordType.py
PyWITS/Objects/Transmission.py
PyWITS/Objects/__init__.py