Metadata-Version: 1.0
Name: PyWITS
Version: 0.1
Summary: WITS0 Serial API
Home-page: xkenneth.blogspot.com
Author: Kenneth Miller
Author-email: xkenneth@gmail.com
License: UNKNOWN
Platform: UNKNOWN
